COPYRIGHT
MANIFEST.in
README.md
pyproject.toml
setup.cfg
setup.py
docs/dev_status.md
docs/nc4_vs_pnetcdf.md
docs/pnetcdf_objects.md
examples/collective_write.py
examples/create_open.py
examples/fill_mode.py
examples/flexible_api.py
examples/get_info.py
examples/ghost_cell.py
examples/global_attribute.py
examples/hints.py
examples/put_varn_int.py
examples/transpose.py
examples/transpose2D.py
include/PnetCDF.pxi
include/mpi-compat.h
src/pnetcdf/_Dimension.pxd
src/pnetcdf/_Dimension.pyx
src/pnetcdf/_File.pxd
src/pnetcdf/_File.pyx
src/pnetcdf/_Variable.pxd
src/pnetcdf/_Variable.pyx
src/pnetcdf/__init__.py
src/pnetcdf/_utils.pxd
src/pnetcdf/_utils.pyx
src/pnetcdf.egg-info/PKG-INFO
src/pnetcdf.egg-info/SOURCES.txt
src/pnetcdf.egg-info/dependency_links.txt
src/pnetcdf.egg-info/requires.txt
src/pnetcdf.egg-info/top_level.txt
test/tst_atts.py
test/tst_default_format.py
test/tst_dims.py
test/tst_file_fill.py
test/tst_file_inq.py
test/tst_file_mode.py
test/tst_rename.py
test/tst_var_bput_var.py
test/tst_var_bput_var1.py
test/tst_var_bput_vara.py
test/tst_var_bput_varm.py
test/tst_var_bput_varn.py
test/tst_var_bput_vars.py
test/tst_var_def_fill.py
test/tst_var_get_var.py
test/tst_var_get_var1.py
test/tst_var_get_vara.py
test/tst_var_get_varm.py
test/tst_var_get_varn.py
test/tst_var_get_vars.py
test/tst_var_iget_var.py
test/tst_var_iget_var1.py
test/tst_var_iget_vara.py
test/tst_var_iget_varm.py
test/tst_var_iget_varn.py
test/tst_var_iget_vars.py
test/tst_var_indexer.py
test/tst_var_iput_var.py
test/tst_var_iput_var1.py
test/tst_var_iput_vara.py
test/tst_var_iput_varm.py
test/tst_var_iput_varn.py
test/tst_var_iput_vars.py
test/tst_var_put_var.py
test/tst_var_put_var1.py
test/tst_var_put_vara.py
test/tst_var_put_varm.py
test/tst_var_put_varn.py
test/tst_var_put_vars.py
test/tst_var_rec_fill.py
test/tst_var_string.py
test/tst_var_type.py
test/tst_version.py
test/tst_wait.py
test/utils.py